Classfile /D:/IdeaProject/deepinjvm/src/main/java/lecture16/Test.class
  Last modified 2019-10-16; size 330 bytes
  MD5 checksum 7c163be9312d47f7bcc3608218b11d2b
  Compiled from "Test.java"
public class lecture16.Test
  minor version: 0
  major version: 52
  flags: ACC_PUBLIC, ACC_SUPER
Constant pool:
   #1 = Methodref          #3.#13         // java/lang/Object."<init>":()V
   #2 = Class              #14            // lecture16/Test
   #3 = Class              #15            // java/lang/Object
   #4 = Utf8               <init>
   #5 = Utf8               ()V
   #6 = Utf8               Code
   #7 = Utf8               LineNumberTable
   #8 = Utf8               foo
   #9 = Utf8               (Ljava/lang/Object;)V
  #10 = Utf8               StackMapTable
  #11 = Utf8               SourceFile
  #12 = Utf8               Test.java
  #13 = NameAndType        #4:#5          // "<init>":()V
  #14 = Utf8               lecture16/Test
  #15 = Utf8               java/lang/Object
{
  public lecture16.Test();
    descriptor: ()V
    flags: ACC_PUBLIC
    Code:
      stack=1, locals=1, args_size=1
         0: aload_0
         1: invokespecial #1                  // Method java/lang/Object."<init>":()V
         4: return
      LineNumberTable:
        line 7: 0

  public static void foo(java.lang.Object);
    descriptor: (Ljava/lang/Object;)V
    flags: ACC_PUBLIC, ACC_STATIC
    Code:
      stack=2, locals=3, args_size=1
         0: iconst_0
         1: istore_1
         2: iconst_0
         3: istore_2
         4: iload_2
         5: sipush        200
         8: if_icmpge     21
        11: iload_1
        12: iload_2
        13: iadd
        14: istore_1
        15: iinc          2, 1
        18: goto          4
        21: return
      LineNumberTable:
        line 9: 0
        line 10: 2
        line 11: 11
        line 10: 15
        line 13: 21
      StackMapTable: number_of_entries = 2
        frame_type = 253 /* append */
          offset_delta = 4
          locals = [ int, int ]
        frame_type = 250 /* chop */
          offset_delta = 16
}
SourceFile: "Test.java"
